drugbank_schemas/__init__.py
drugbank_schemas/models/__init__.py
drugbank_schemas/models/drugbank_latest.py
drugbank_schemas/models/drugbank_v3_0.py
drugbank_schemas/models/drugbank_v4_1.py
drugbank_schemas/models/drugbank_v4_2.py
drugbank_schemas/models/drugbank_v4_3.py
drugbank_schemas/models/drugbank_v4_6.py
drugbank_schemas/models/drugbank_v5_0.py
drugbank_schemas-0.1.1.dist-info/METADATA
drugbank_schemas-0.1.1.dist-info/WHEEL
drugbank_schemas-0.1.1.dist-info/licenses/LICENSE
drugbank_schemas-0.1.1.dist-info/RECORD
