Metadata-Version: 2.4
Name: drugbank-schemas
Version: 0.1.1
Summary: Drugbank Schemas Pydantic Models
Project-URL: Repository, https://github.com/ndonyapour/drugbank_schemas
Author-email: Nazanin Donyapour <nazanin.donyapour@nih.gov>
License-File: LICENSE
Classifier: Development Status :: 4 - Beta
Classifier: License :: OSI Approved :: MIT License
Classifier: Operating System :: OS Independent
Classifier: Programming Language :: Python :: 3.10
Classifier: Programming Language :: Python :: 3.11
Classifier: Programming Language :: Python :: 3.12
Classifier: Topic :: Scientific/Engineering :: Bio-Informatics
Classifier: Topic :: Scientific/Engineering :: Information Analysis
Classifier: Topic :: Scientific/Engineering :: Medical Science Apps.
Classifier: Topic :: Text Processing :: Markup :: XML
Requires-Python: >=3.9
Requires-Dist: bump-my-version>=0.29.0
Requires-Dist: coverage-badge==1.1.0
Requires-Dist: mypy>=1.14.1
Requires-Dist: nox==2023.4.22
Requires-Dist: pre-commit==3.3.2
Requires-Dist: pytest-cov==4.1.0
Requires-Dist: pytest-xdist==3.3.1
Requires-Dist: pytest==7.4
Requires-Dist: requests==2.31.0
Requires-Dist: ruff>=0.9.1
Requires-Dist: xsdata-pydantic[cli,lxml,soap]>=24.5
